jarvis/__init__.py
jarvis/call/__init__.py
jarvis/call/recognizer.py
Upender_recognizer-0.0.14.dist-info/METADATA
Upender_recognizer-0.0.14.dist-info/WHEEL
Upender_recognizer-0.0.14.dist-info/licence.txt
Upender_recognizer-0.0.14.dist-info/top_level.txt
Upender_recognizer-0.0.14.dist-info/RECORD
