Metadata-Version: 2.1
Name: Upender-recognizer
Version: 0.0.14
Summary: Converting handwritten (digits) information to digital format
Home-page: https://github.com/UpenderKaveti/Real-time-handwritten-digits-recognition-using-Convolutional-Neural-Network
Author: Upender_Kaveti
Author-email: artificalintelligence021@gmail.com
License: UNKNOWN
Keywords: handwritten,digits,recognition,OCR
Platform: UNKNOWN
Classifier: Programming Language :: Python :: 3
Classifier: License :: OSI Approved :: MIT License
Classifier: Operating System :: OS Independent
Requires-Python: >=3.6
License-File: licence.txt
Requires-Dist: pandas
Requires-Dist: numpy
Requires-Dist: scikit-learn
Requires-Dist: scikit-optimize
Requires-Dist: matplotlib
Requires-Dist: tensorflow
Requires-Dist: keras
Requires-Dist: gdown
Requires-Dist: opencv-python
